gitlab_cq/__init__.py
gitlab_cq/__main__.py
gitlab_cq/__version__.py
gitlab_cq/gcc.py
gitlab_cq/mypy.py
gitlab_cq/pyright.py
gitlab_cq/ruff.py
gitlab_cq-0.2.0.dist-info/LICENSE.txt
gitlab_cq-0.2.0.dist-info/METADATA
gitlab_cq-0.2.0.dist-info/WHEEL
gitlab_cq-0.2.0.dist-info/entry_points.txt
gitlab_cq-0.2.0.dist-info/top_level.txt
gitlab_cq-0.2.0.dist-info/RECORD
