Metadata-Version: 2.1
Name: gitlab-cq
Version: 0.2.0
Summary: Parse linter output and convert it to GitLab Code Quality report
Author-email: Yoshiki Matsuda <y_matsuda@fixstars.com>
Maintainer-email: Yoshiki Matsuda <y_matsuda@fixstars.com>
License: MIT License
Project-URL: Repository, https://github.com/yosh-matsuda/gitlab-cq
Keywords: linter,gitlab,code quality,report,ruff,pyright,mypy,gcc,clang,clang-tidy
Classifier: Environment :: Console
Classifier: Development Status :: 4 - Beta
Classifier: Intended Audience :: Developers
Classifier: Topic :: Software Development :: Libraries :: Python Modules
Classifier: Operating System :: POSIX :: Linux
Classifier: Operating System :: Microsoft :: Windows
Classifier: Operating System :: MacOS :: MacOS X
Classifier: Programming Language :: Python :: 3.8
Classifier: Programming Language :: Python :: 3.9
Classifier: Programming Language :: Python :: 3.10
Classifier: Programming Language :: Python :: 3.11
Classifier: Programming Language :: Python :: 3.12
Requires-Python: >=3.8
License-File: LICENSE.txt
Requires-Dist: typing-extensions
